udb_py/__init__.py
udb_py/aggregate.py
udb_py/common.py
udb_py/udb.py
udb_py/udb_core.py
udb_py/udb_index.py
udb_py/udb_storage.py
udb_py/udb_view.py
udb_py/index/__init__.py
udb_py/index/udb_base_geo_index.py
udb_py/index/udb_base_linear_index.py
udb_py/index/udb_base_text_index.py
udb_py/index/udb_btree_base_index.py
udb_py/index/udb_btree_index.py
udb_py/index/udb_btree_uniq_index.py
udb_py/index/udb_clustered_index.py
udb_py/index/udb_hash_base_index.py
udb_py/index/udb_hash_index.py
udb_py/index/udb_hash_uniq_index.py
udb_py/index/udb_rtree_index.py
udb_py/index/udb_text_index.py
udb_py/storage/__init__.py
udb_py/storage/udb_json_file_storage.py
udb_py/storage/udb_wal_storage.py
udb_py-0.0.3.dist-info/LICENSE
udb_py-0.0.3.dist-info/METADATA
udb_py-0.0.3.dist-info/WHEEL
udb_py-0.0.3.dist-info/top_level.txt
udb_py-0.0.3.dist-info/RECORD
