Metadata-Version: 2.1
Name: udb-py
Version: 0.0.3
Summary: In-memory database
Home-page: https://github.com/akaterra/udb.py
License: MIT
License-File: LICENSE
